conf.py
copyallmp4.py
downDy.py
out_dutys.py
spyderBili.py
turn2release.py
asa_tools-0.1.15.dist-info/METADATA
asa_tools-0.1.15.dist-info/WHEEL
asa_tools-0.1.15.dist-info/entry_points.txt
asa_tools-0.1.15.dist-info/top_level.txt
asa_tools-0.1.15.dist-info/RECORD
