Metadata-Version: 2.1
Name: asa-tools
Version: 0.1.15
Summary: asa's personal toolbox
Classifier: Development Status :: 3 - Alpha
Classifier: Intended Audience :: Developers
Classifier: Topic :: Software Development :: Build Tools
Classifier: License :: OSI Approved :: MIT License
Classifier: Programming Language :: Python :: 3.10
Classifier: Programming Language :: Python :: 3.11
Requires-Dist: Click
Requires-Dist: openpyxl
Requires-Dist: requests
Requires-Dist: tqdm
Requires-Dist: parsel
